gtraceroute/__init__.py
gtraceroute/core/__init__.py
gtraceroute/core/tracer.py
gtraceroute/core/utils.py
gtraceroute/core/application/__init__.py
gtraceroute/core/application/services.py
gtraceroute/core/transport/__init__.py
gtraceroute/core/transport/entities.py
gtraceroute/core/transport/services.py
gtraceroute/tui/__init__.py
gtraceroute/tui/app.css
gtraceroute/tui/app.py
gtraceroute/tui/widgets/__init__.py
gtraceroute/tui/widgets/hop_list.py
gtraceroute/tui/widgets/hop_list_item.py
gtraceroute/tui/widgets/hop_sparkline.py
gtraceroute/tui/widgets/target_input.py
gtraceroute/tui/widgets/target_list.py
gtraceroute/tui/widgets/tracer_widget.py
gtraceroute-0.1.1.dist-info/LICENSE
gtraceroute-0.1.1.dist-info/METADATA
gtraceroute-0.1.1.dist-info/WHEEL
gtraceroute-0.1.1.dist-info/entry_points.txt
gtraceroute-0.1.1.dist-info/top_level.txt
gtraceroute-0.1.1.dist-info/RECORD
