Metadata-Version: 2.1
Name: gtraceroute
Version: 0.1.1
Summary: gtraceroute is a sophisticated network diagnostic tool.
Author-email: Levi Borodenko <levi.borodenko@gmail.com>
License: MIT
Classifier: Programming Language :: Python :: 3.11
Requires-Python: >=3.11
License-File: LICENSE
Requires-Dist: textual (==0.29)
Provides-Extra: dev
Requires-Dist: textual-dev ; extra == 'dev'
Requires-Dist: black ; extra == 'dev'
Requires-Dist: pytest ; extra == 'dev'
Requires-Dist: pytest-asyncio ; extra == 'dev'
Requires-Dist: pre-commit ; extra == 'dev'
Requires-Dist: mypy ; extra == 'dev'
Requires-Dist: build ; extra == 'dev'
Requires-Dist: twine ; extra == 'dev'
